{
	"jsonResults": {
		"dateRun": "07-May-2025 15:36:37",
		"ini_time_size": "07-May-2025 15:36:04 9257B  MD5 = e1370b7b989bd43030dac73709179a9e",
		"version": "Imatest 24.2.6 Master Color/Tone Auto",
		"build": "2025-03-20",
		"image_file": "car_55.0 mm_6400ISO_+1EV_Dist2_OFF_Focused.tiff",
		"ColorSpace": "sRGB",
		"Reference": "Default values",
		"Ref_folder": "/usr/local/Imatest/v24.2/Master/",
		"Gamma": [0.397],
		"patches_for_gamma_start_end": [1,5],
		"exposure_error_normalized_y_channel": [0.0355],
		"mean_camera_Saturation_Pct": ["_NaN_"],
		"mean_chroma_level_CPIQ_Pct": ["_NaN_"],
		"CPIQ_chroma_quality_loss_JND": ["_NaN_"],
		"CPIQ_exposure_quality_loss_JND": ["_NaN_"],
		"pixel_offset": [0],
		"mean_patch_size_pxls": [246,305],
		"roi_settings": "Recent ROI settings are in roi, nwid_save, nht_save, fillf, and distort (same names as ini file)",
		"roi": [2997,1320,4753,1747,2997,1752,4753,1307],
		"nwid_save": [6024],
		"nht_save": [4020],
		"fillf": [0.7],
		"distort": [0],
		"grayscale_zone": [1,2,3,4,5],
		"grayscale_minus_log_exposure": [2,1.513,1.025,0.5375,0.05],
		"grayscale_Y_reflectivity": [0.01,0.03073,0.09441,0.2901,0.8913],
		"grayscale_Y_Printer_pixel_gamma22": [33.13,55.18,91.91,153.1,255],
		"grayscale_Y_density": [0.1074,0.2176,0.3795,0.6047,0.9472],
		"grayscale_R_density": [0.1081,0.22,0.3852,0.6127,0.942],
		"grayscale_G_density": [0.1084,0.2173,0.3783,0.6028,0.9481],
		"grayscale_B_density": [0.09561,0.2135,0.3746,0.6004,0.9547],
		"grayscale_Y_mean": [199.1,154.5,106.4,63.37,28.79],
		"grayscale_R_mean": [198.8,153.7,105,62.2,29.14],
		"grayscale_G_mean": [198.7,154.6,106.7,63.65,28.74],
		"grayscale_B_mean": [204.6,156,107.6,64,28.3],
		"White_Bal_error_Degrees": [303.4,141.1,212.4,221.4,-183.1],
		"White_Bal_error_Mired": [-6.862,-3.269,-4.868,-5.068,4.458],
		"White_Bal_error_S_HSV": [0.02894,0.01488,0.02415,0.02798,0.0288],
		"White_Bal_error_Delta_C_ab": [3.161,0.845,0.8736,0.6793,0.3749],
		"White_Bal_error_Delta_C_94": [3.161,0.845,0.8736,0.6793,0.3749],
		"White_Bal_error_Delta_C_00": [3.169,0.8341,0.9951,0.8809,0.3828],
		"n_Patch": [1,2,3,4,5],
		"n_Row": [1,1,1,1,1],
		"n_Column": [1,2,3,4,5],
		"width_pixels": [247,247,247,247,246],
		"height_pixels": [307,307,307,307,308],
		"Pixels_total": [75829,75829,75829,75829,75768],
		"R_reference": [242.4,146.6,86.6,49.01,25.46],
		"G_reference": [242.4,146.6,86.6,49.01,25.46],
		"B_reference": [242.4,146.6,86.6,49.01,25.46],
		"R_input": [198.8,153.7,105,62.2,29.14],
		"G_input": [198.7,154.6,106.7,63.65,28.74],
		"B_input": [204.6,156,107.6,64,28.3],
		"L_reference": [95.63,60.79,36.82,20.33,8.991],
		"a_reference": [0,0,0,0,0],
		"b_reference": [0,0,0,0,0],
		"L_input": [80.3,63.8,44.99,26.81,10.66],
		"a_input": [1.15,-0.08231,-0.4673,-0.5263,0.08263],
		"b_input": [-2.945,-0.841,-0.7381,-0.4295,0.3657],
		"x_reference": [0.3127,0.3127,0.3127,0.3127,0.3127],
		"y_reference": [0.329,0.329,0.329,0.329,0.329],
		"Y_reference": [0.8913,0.2901,0.09441,0.03073,0.01],
		"x_input": [0.3085,0.3105,0.3092,0.3089,0.3159],
		"y_input": [0.3219,0.3269,0.3271,0.3278,0.3316],
		"Y_input": [0.5721,0.3255,0.1454,0.05028,0.01215],
		"LUV_comment": "L2 is used to differentiate between the L in LAB and L in LUV.",
		"L2_reference": [805.1,262,85.28,27.75,9.033],
		"U_reference": [0.1978,0.1978,0.1978,0.1978,0.1978],
		"V_reference": [0.4683,0.4683,0.4683,0.4683,0.4683],
		"L2_input": [516.8,294.1,131.3,45.42,10.97],
		"U_input": [0.1976,0.1971,0.1961,0.1957,0.199],
		"V_input": [0.4639,0.4669,0.4668,0.4671,0.4702],
		"patch_numbers_for_all_Delta_E_C": [1,2,3,4,5],
		"Delta_E_all": [15.7,3.13,8.22,6.52,1.71],
		"Delta_C_all": [3.16,0.845,0.874,0.679,0.375],
		"Delta_E94_all": [15.7,3.13,8.22,6.52,1.71],
		"Delta_C94_all": [3.16,0.845,0.874,0.679,0.375],
		"Delta_E2000_all": [10.3,2.7,7.35,4.74,1.11],
		"Delta_C2000_all": [3.17,0.834,0.995,0.881,0.383],
		"Delta_L_all": [-15.3,3.01,8.18,6.48,1.67],
		"Delta_Chroma_all": [3.16,0.845,0.874,0.679,0.375],
		"Delta_Hue_Distance_all": [0,0,0,0,0],
		"Delta_Hue_Degrees_all": [0,0,0,0,0],
		"sat_corr_comment": "sat_corr explained on https://www.imatest.com/docs/colorcheck/#satcorr - not recommended.",
		"Delta_C_all_sat_corr": ["_NaN_","_NaN_","_NaN_","_NaN_","_NaN_"],
		"Delta_C94_all_sat_corr": ["_NaN_","_NaN_","_NaN_","_NaN_","_NaN_"],
		"Delta_C2000_all_sat_corr": ["_NaN_","_NaN_","_NaN_","_NaN_","_NaN_"],
		"grayscale_patch_numbers": [1,2,3,4,5],
		"Delta_E": [15.7,3.13,8.22,6.52,1.71],
		"Delta_C": [3.16,0.845,0.874,0.679,0.375],
		"Delta_E94": [15.7,3.13,8.22,6.52,1.71],
		"Delta_C94": [3.16,0.845,0.874,0.679,0.375],
		"Delta_E2000": [10.3,2.7,7.35,4.74,1.11],
		"Delta_C2000": [3.17,0.834,0.995,0.881,0.383],
		"Delta_L": [-15.3,3.01,8.18,6.48,1.67],
		"Delta_Chroma": [3.16,0.845,0.874,0.679,0.375],
		"Delta_Hue_Distance": [0,0,0,0,0],
		"Delta_Hue_Degrees": [0,0,0,0,0],
		"mean_Delta_E": [7.05],
		"mean_Delta_C": [1.19],
		"mean_Delta_E94": [7.05],
		"mean_Delta_C94": [1.19],
		"mean_Delta_E2000": [5.24],
		"mean_Delta_C2000": [1.25],
		"mean_Delta_L": [0.801],
		"mean_Delta_Chroma": [1.19],
		"mean_Delta_Hue_Distance": [0],
		"mean_Delta_Hue_Degrees": [0],
		"mean_Delta_C_sat_corr": ["_NaN_"],
		"mean_Delta_C94_sat_corr": ["_NaN_"],
		"mean_Delta_C2000_sat_corr": ["_NaN_"],
		"max_Delta_E": [15.7],
		"max_Delta_C": [3.16],
		"max_Delta_E94": [15.7],
		"max_Delta_C94": [3.16],
		"max_Delta_E2000": [10.3],
		"max_Delta_C2000": [3.17],
		"max_Delta_L": [8.18],
		"max_Delta_Chroma": [3.16],
		"max_Delta_Hue_Distance": [0],
		"max_Delta_Hue_Degrees": [0],
		"max_Delta_C_sat_corr": ["_NaN_"],
		"max_Delta_C94_sat_corr": ["_NaN_"],
		"max_Delta_C2000_sat_corr": ["_NaN_"],
		"mean_RegionSize": [75570],
		"Sequence_dark_to_light": [5,4,3,2,1],
		"Patch_number": [5,4,3,2,1],
		"R_noise": [0.07158,0.0633,0.04678,0.03865,0.03494],
		"G_noise": [0.04959,0.03403,0.02806,0.02527,0.02393],
		"B_noise": [0.06115,0.045,0.03518,0.03001,0.02735],
		"R_SNR_ratio": [1.596,3.854,8.804,15.59,22.32],
		"G_SNR_ratio": [2.273,7.335,14.91,24,32.56],
		"B_SNR_ratio": [1.815,5.576,12,20.38,29.34],
		"R_SNR_dB": [4.063,11.72,18.89,23.86,26.97],
		"G_SNR_dB": [7.131,17.31,23.47,27.6,30.25],
		"B_SNR_dB": [5.177,14.93,21.58,26.18,29.35],
		"Gb_noise": [0.04016,0.02895,0.02359,0.02104,0.01978],
		"Gb_SNR_ratio": [2.812,8.583,17.69,28.8,39.48],
		"Gb_SNR_dB": [8.979,18.67,24.96,29.19,31.93],
		"Y_f_stop_SNR_ratio": [5.463,5.335,4.678,3.246,2.084],
		"Y_f_stop_SNR_dB": [14.75,14.54,13.4,10.23,6.379],
		"quality_levels_for_DR": [
				"Low,",
				"Medium,",
				"M-H,",
				"High,"
		],
		"SigNoise_levels_for_DR": [1,0.5,0.25,0.1],
		"Dynamic_Range_f_stops": [0,0,3.861,0],
		"Dynamic_Range_dB": [0,0,23.25,0],
		"noise_ISO15739_pct": [0.4643,0.4711,0.9576,2.082,2.69],
		"snr_ISO15739": [2.616,10.67,15.18,15.63,21.27],
		"noise_pct_ISO15739_at_13pct_Lref": [1.964],
		"snr_ISO15739_at_13pct_Lref": [15.59],
		"snr_dB_ISO15739_at_13pct_Lref": [23.85],
		"DynamicRange_at_density_2": [496.6],
		"DynamicRange_total": [0],
		"DynamicRange_from_slope_OD": [1.95],
		"DynamicRange_from_slope_EV": [6.474],
		"DynamicRange_from_slope_dB": [39],
		"SNR_BW_dB_RGBY": [22.78,26.47,24.98,28.07],
		"L_noise": [4.493,3.158,2.421,2.027,1.817],
		"a_noise": [11.53,8.65,6.325,5.06,4.448],
		"b_noise": [11.1,8.017,5.903,4.681,4.129],
		"Total_Lab_noise_unwtd": [16.62,12.21,8.984,7.185,6.335],
		"Total_ab_noise_unwtd": [16,11.79,8.651,6.893,6.069],
		"R_minus_Y_KK_noise": [0.06351,0.05371,0.03992,0.03342,0.03043],
		"B_minus_Y_KK_noise": [0.06809,0.0488,0.03861,0.03269,0.03024],
		"Y_Kelly_Keelan_noise": [0.04016,0.02895,0.02359,0.02104,0.01978],
		"Total_KK_noise": [0.05609,0.04304,0.03365,0.02913,0.02702],
		"Chroma_KK_noise": [0.03916,0.03185,0.024,0.02014,0.01841],
		"Total_old_iso_noise": [0.07026,0.05537,0.0426,0.03645,0.03362],
		"Y_noise_from_YUV": [0.04016,0.02895,0.02359,0.02104,0.01978],
		"U_noise_from_YUV": [0.03199,0.02293,0.01814,0.01536,0.01421],
		"V_noise_from_YUV": [0.04959,0.04194,0.03117,0.0261,0.02376],
		"Total_UV_noise_from_YUV": [0.05902,0.0478,0.03607,0.03029,0.02769],
		"R_minus_Y_KK_SNR_dB": [4.999,13.31,20.39,25.17,28.19],
		"B_minus_Y_KK_SNR_dB": [4.394,14.14,20.68,25.36,28.24],
		"Y_Kelly_Keelan_SNR_dB": [8.979,18.67,24.96,29.19,31.93],
		"Total_KK_SNR_dB": [6.077,15.23,21.87,26.36,29.22],
		"Chroma_KK_SNR_dB": [9.199,17.84,24.81,29.57,32.55],
		"Total_old_iso_SNR_dB": [4.122,13.04,19.82,24.41,27.32],
		"Y_SNR_dB_from_YUV": [8.98,18.67,24.96,29.19,31.93],
		"U_SNR_dB_from_YUV": [10.95,20.7,27.24,31.92,34.8],
		"V_SNR_dB_from_YUV": [7.147,15.45,22.53,27.32,30.33],
		"Total_UV_SNR_dB_from_YUV": [5.636,14.32,21.27,26.02,29.01],
		"gain_incremental": [0.735,1.01,2.46,6.15,8.65],
		"SNR_ISO_Q": [0.589],
		"VN_distance_1_cm": [40],
		"VN_height_1_cm": [25],
		"VN_angle_1_deg": [34.71],
		"VN_mean_L_1": [11.78,27.2,45.15,63.89,80.39],
		"VN_sigma_L_1": [3.9,2.64,2.133,1.878,1.706],
		"VN_sigma_u_1": [3.136,3.36,3.062,2.838,2.671],
		"VN_sigma_v_1": [1.293,1.357,1.325,1.301,1.285],
		"VN_sigma_Visnoise_1": [6.99,5.941,5.17,4.715,4.397],
		"VN_SNR_L_1": [3.019,10.3,21.17,34.03,47.12],
		"VN_SNR_u_1": [3.755,8.095,14.74,22.52,30.1],
		"VN_SNR_v_1": [9.106,20.04,34.07,49.11,62.58],
		"VN_SNR_Visnoise_1": [1.685,4.578,8.734,13.55,18.28],
		"EXIF_results": [
				"File Modification Date/Time     , 2025:04:22 20:54:59+02:00",
				"Image Width                     , 6024",
				"Image Height                    , 4020"
		]
	}
}
