{
	"jsonResults": {
		"dateRun": "12-May-2025 19:52:26",
		"ini_time_size": "12-May-2025 19:44:17 10119B  MD5 = 65cb115b26c4a9a12b5ef69694c39d47",
		"version": "Imatest 24.2.6 Master Color/Tone Auto",
		"build": "2025-03-20",
		"image_file": "car_18.0 mm_25600ISO_-1EV_Dist1_ON_Focused.tiff",
		"ColorSpace": "sRGB",
		"Reference": "Default values",
		"Ref_folder": "/usr/local/Imatest/v24.2/Master/",
		"Gamma": [0.3862],
		"patches_for_gamma_start_end": [1,5],
		"exposure_error_normalized_y_channel": [-0.171],
		"mean_camera_Saturation_Pct": ["_NaN_"],
		"mean_chroma_level_CPIQ_Pct": ["_NaN_"],
		"CPIQ_chroma_quality_loss_JND": ["_NaN_"],
		"CPIQ_exposure_quality_loss_JND": ["_NaN_"],
		"pixel_offset": [0],
		"mean_patch_size_pxls": [69,76],
		"roi_settings": "Recent ROI settings are in roi, nwid_save, nht_save, fillf, and distort (same names as ini file)",
		"roi": [3081,1832,3511,1921,3081,1923,3511,1824],
		"nwid_save": [6024],
		"nht_save": [4020],
		"fillf": [0.8],
		"distort": [0],
		"grayscale_zone": [1,2,3,4,5],
		"grayscale_minus_log_exposure": [2,1.513,1.025,0.5375,0.05],
		"grayscale_Y_reflectivity": [0.01,0.03073,0.09441,0.2901,0.8913],
		"grayscale_Y_Printer_pixel_gamma22": [33.13,55.18,91.91,153.1,255],
		"grayscale_Y_density": [0.3038,0.4204,0.6086,0.8625,1.073],
		"grayscale_R_density": [0.311,0.437,0.6244,0.804,0.9529],
		"grayscale_G_density": [0.3058,0.4181,0.6067,0.8876,1.129],
		"grayscale_B_density": [0.2641,0.3956,0.5828,0.8083,0.9674],
		"grayscale_Y_mean": [126.7,96.86,62.79,35,21.57],
		"grayscale_R_mean": [124.6,93.22,60.55,40.04,28.42],
		"grayscale_G_mean": [126.1,97.37,63.07,33.03,18.94],
		"grayscale_B_mean": [138.8,102.6,66.64,39.65,27.49],
		"White_Bal_error_Degrees": [1296,928.9,877.8,119.5,46.25],
		"White_Bal_error_Mired": [-25.58,-19.24,-18.31,-2.777,-1.087],
		"White_Bal_error_S_HSV": [0.1022,0.09098,0.09137,0.175,0.3335],
		"White_Bal_error_Delta_C_ab": [7.368,3.535,2.562,5.822,7.921],
		"White_Bal_error_Delta_C_94": [7.368,3.535,2.562,5.822,7.921],
		"White_Bal_error_Delta_C_00": [6.59,3.309,2.432,6.757,8.775],
		"n_Patch": [1,2,3,4,5],
		"n_Row": [1,1,1,1,1],
		"n_Column": [1,2,3,4,5],
		"width_pixels": [70,70,70,70,70],
		"height_pixels": [78,78,78,78,78],
		"Pixels_total": [5460,5460,5460,5460,5460],
		"R_reference": [242.4,146.6,86.6,49.01,25.46],
		"G_reference": [242.4,146.6,86.6,49.01,25.46],
		"B_reference": [242.4,146.6,86.6,49.01,25.46],
		"R_input": [124.6,93.22,60.55,40.04,28.42],
		"G_input": [126.1,97.37,63.07,33.03,18.94],
		"B_input": [138.8,102.6,66.64,39.65,27.49],
		"L_reference": [95.63,60.79,36.82,20.33,8.991],
		"a_reference": [0,0,0,0,0],
		"b_reference": [0,0,0,0,0],
		"L_input": [53.1,41.1,26.57,13.78,7.208],
		"a_input": [2.116,-0.4722,-0.2072,4.867,6.748],
		"b_input": [-7.058,-3.504,-2.554,-3.195,-4.148],
		"x_reference": [0.3127,0.3127,0.3127,0.3127,0.3127],
		"y_reference": [0.329,0.329,0.329,0.329,0.329],
		"Y_reference": [0.8913,0.2901,0.09441,0.03073,0.01],
		"x_input": [0.2974,0.2996,0.3004,0.3156,0.3197],
		"y_input": [0.3063,0.317,0.3171,0.2969,0.2755],
		"Y_input": [0.2114,0.1193,0.04941,0.01692,0.00798],
		"LUV_comment": "L2 is used to differentiate between the L in LAB and L in LUV.",
		"L2_reference": [805.1,262,85.28,27.75,9.033],
		"U_reference": [0.1978,0.1978,0.1978,0.1978,0.1978],
		"V_reference": [0.4683,0.4683,0.4683,0.4683,0.4683],
		"L2_input": [190.9,107.7,44.63,15.29,7.208],
		"U_input": [0.1956,0.1931,0.1936,0.2128,0.2256],
		"V_input": [0.4533,0.4598,0.46,0.4505,0.4376],
		"patch_numbers_for_all_Delta_E_C": [1,2,3,4,5],
		"Delta_E_all": [43.2,20,10.6,8.76,8.12],
		"Delta_C_all": [7.37,3.54,2.56,5.82,7.92],
		"Delta_E94_all": [43.2,20,10.6,8.76,8.12],
		"Delta_C94_all": [7.37,3.54,2.56,5.82,7.92],
		"Delta_E2000_all": [32,19.9,8.45,8.06,8.84],
		"Delta_C2000_all": [6.59,3.31,2.43,6.76,8.77],
		"Delta_L_all": [-42.5,-19.7,-10.3,-6.55,-1.78],
		"Delta_Chroma_all": [7.37,3.54,2.56,5.82,7.92],
		"Delta_Hue_Distance_all": [0,0,0,0,0],
		"Delta_Hue_Degrees_all": [0,0,0,0,0],
		"sat_corr_comment": "sat_corr explained on https://www.imatest.com/docs/colorcheck/#satcorr - not recommended.",
		"Delta_C_all_sat_corr": ["_NaN_","_NaN_","_NaN_","_NaN_","_NaN_"],
		"Delta_C94_all_sat_corr": ["_NaN_","_NaN_","_NaN_","_NaN_","_NaN_"],
		"Delta_C2000_all_sat_corr": ["_NaN_","_NaN_","_NaN_","_NaN_","_NaN_"],
		"grayscale_patch_numbers": [1,2,3,4,5],
		"Delta_E": [43.2,20,10.6,8.76,8.12],
		"Delta_C": [7.37,3.54,2.56,5.82,7.92],
		"Delta_E94": [43.2,20,10.6,8.76,8.12],
		"Delta_C94": [7.37,3.54,2.56,5.82,7.92],
		"Delta_E2000": [32,19.9,8.45,8.06,8.84],
		"Delta_C2000": [6.59,3.31,2.43,6.76,8.77],
		"Delta_L": [-42.5,-19.7,-10.3,-6.55,-1.78],
		"Delta_Chroma": [7.37,3.54,2.56,5.82,7.92],
		"Delta_Hue_Distance": [0,0,0,0,0],
		"Delta_Hue_Degrees": [0,0,0,0,0],
		"mean_Delta_E": [18.1],
		"mean_Delta_C": [5.44],
		"mean_Delta_E94": [18.1],
		"mean_Delta_C94": [5.44],
		"mean_Delta_E2000": [15.4],
		"mean_Delta_C2000": [5.57],
		"mean_Delta_L": [-16.2],
		"mean_Delta_Chroma": [5.44],
		"mean_Delta_Hue_Distance": [0],
		"mean_Delta_Hue_Degrees": [0],
		"mean_Delta_C_sat_corr": ["_NaN_"],
		"mean_Delta_C94_sat_corr": ["_NaN_"],
		"mean_Delta_C2000_sat_corr": ["_NaN_"],
		"max_Delta_E": [43.2],
		"max_Delta_C": [7.92],
		"max_Delta_E94": [43.2],
		"max_Delta_C94": [7.92],
		"max_Delta_E2000": [32],
		"max_Delta_C2000": [8.77],
		"max_Delta_L": [-1.78],
		"max_Delta_Chroma": [7.92],
		"max_Delta_Hue_Distance": [0],
		"max_Delta_Hue_Degrees": [0],
		"max_Delta_C_sat_corr": ["_NaN_"],
		"max_Delta_C94_sat_corr": ["_NaN_"],
		"max_Delta_C2000_sat_corr": ["_NaN_"],
		"mean_RegionSize": [5390],
		"Sequence_dark_to_light": [5,4,3,2,1],
		"Patch_number": [5,4,3,2,1],
		"R_noise": [0.09728,0.1161,0.1238,0.106,0.08024],
		"G_noise": [0.07924,0.09054,0.08524,0.06203,0.05382],
		"B_noise": [0.0907,0.1024,0.09768,0.07215,0.05805],
		"R_SNR_ratio": [1.146,1.352,1.919,3.449,6.09],
		"G_SNR_ratio": [0.9373,1.431,2.902,6.156,9.188],
		"B_SNR_ratio": [1.189,1.519,2.675,5.574,9.377],
		"R_SNR_dB": [1.181,2.619,5.659,10.75,15.69],
		"G_SNR_dB": [-0.5621,3.111,9.253,15.79,19.26],
		"B_SNR_dB": [1.5,3.631,8.548,14.92,19.44],
		"Gb_noise": [0.06484,0.07278,0.06934,0.05409,0.04552],
		"Gb_SNR_ratio": [1.305,1.886,3.551,7.023,10.91],
		"Gb_SNR_dB": [2.31,5.51,11.01,16.93,20.76],
		"Y_f_stop_SNR_ratio": [1.587,1.431,1.08,0.6856,0.5015],
		"Y_f_stop_SNR_dB": [4.012,3.11,0.6692,-3.278,-5.994],
		"quality_levels_for_DR": [
				"Low,",
				"Medium,",
				"M-H,",
				"High,"
		],
		"SigNoise_levels_for_DR": [1,0.5,0.25,0.1],
		"Dynamic_Range_f_stops": [3.464,0,0,0],
		"Dynamic_Range_dB": [20.86,0,0,0],
		"noise_ISO15739_pct": [0.8268,1.209,2.367,4.131,4.771],
		"snr_ISO15739": [0.9652,1.4,2.088,2.887,4.43],
		"noise_pct_ISO15739_at_13pct_Lref": [4.431],
		"snr_ISO15739_at_13pct_Lref": [3.611],
		"snr_dB_ISO15739_at_13pct_Lref": [11.15],
		"DynamicRange_at_density_2": [516.7],
		"DynamicRange_total": [390.4],
		"DynamicRange_from_slope_OD": [1.95],
		"DynamicRange_from_slope_EV": [6.474],
		"DynamicRange_from_slope_dB": [39],
		"SNR_BW_dB_RGBY": [10.61,15.27,13.95,16.45],
		"L_noise": [7.155,7.886,7.093,5.396,4.466],
		"a_noise": [15.21,17.84,17.07,12.65,10.22],
		"b_noise": [15.59,17.99,16.62,12.13,9.62],
		"Total_Lab_noise_unwtd": [22.92,26.53,24.86,18.34,14.73],
		"Total_ab_noise_unwtd": [21.77,25.34,23.82,17.53,14.04],
		"R_minus_Y_KK_noise": [0.08756,0.1062,0.1102,0.08702,0.06758],
		"B_minus_Y_KK_noise": [0.0967,0.113,0.1082,0.07939,0.06538],
		"Y_Kelly_Keelan_noise": [0.06484,0.07278,0.06934,0.05409,0.04552],
		"Total_KK_noise": [0.08465,0.0978,0.09604,0.07478,0.06101],
		"Chroma_KK_noise": [0.05442,0.06533,0.06646,0.05165,0.04062],
		"Total_old_iso_noise": [0.103,0.1206,0.1202,0.0937,0.07536],
		"Y_noise_from_YUV": [0.06483,0.07277,0.06933,0.05408,0.04552],
		"U_noise_from_YUV": [0.04544,0.0531,0.05083,0.0373,0.03072],
		"V_noise_from_YUV": [0.06838,0.0829,0.08604,0.06796,0.05277],
		"Total_UV_noise_from_YUV": [0.0821,0.09845,0.09993,0.07752,0.06106],
		"R_minus_Y_KK_SNR_dB": [-0.2996,2.231,6.985,12.8,17.33],
		"B_minus_Y_KK_SNR_dB": [-1.163,1.688,7.145,13.6,17.62],
		"Y_Kelly_Keelan_SNR_dB": [2.31,5.51,11.01,16.93,20.76],
		"Total_KK_SNR_dB": [-0.006462,2.943,8.178,14.12,18.22],
		"Chroma_KK_SNR_dB": [3.831,6.448,11.38,17.33,21.75],
		"Total_old_iso_SNR_dB": [-1.71,1.121,6.229,12.16,16.38],
		"Y_SNR_dB_from_YUV": [2.311,5.511,11.01,16.93,20.76],
		"U_SNR_dB_from_YUV": [5.399,8.249,13.71,20.16,24.18],
		"V_SNR_dB_from_YUV": [1.849,4.38,9.133,14.95,19.48],
		"Total_UV_SNR_dB_from_YUV": [0.2605,2.887,7.833,13.8,18.21],
		"gain_incremental": [0.954,1.31,2.93,6.02,7.84],
		"SNR_ISO_Q": [0.309],
		"VN_distance_1_cm": [40],
		"VN_height_1_cm": [25],
		"VN_angle_1_deg": [34.71],
		"VN_mean_L_1": [10.27,16.41,28.06,41.69,53.38],
		"VN_sigma_L_1": [5.638,6.744,5.657,4.688,3.935],
		"VN_sigma_u_1": [4.626,6.217,7.093,6.405,5.94],
		"VN_sigma_v_1": [2.027,3.242,3.685,3.325,3.238],
		"VN_sigma_Visnoise_1": [10.23,13.09,12.89,11.22,10.04],
		"VN_SNR_L_1": [1.822,2.433,4.96,8.893,13.56],
		"VN_SNR_u_1": [2.221,2.64,3.956,6.508,8.986],
		"VN_SNR_v_1": [5.068,5.062,7.614,12.54,16.48],
		"VN_SNR_Visnoise_1": [1.004,1.254,2.177,3.716,5.315],
		"EXIF_results": [
				"File Modification Date/Time     , 2025:04:22 20:48:40+02:00",
				"Image Width                     , 6024",
				"Image Height                    , 4020"
		]
	}
}
