{
	"jsonResults": {
		"dateRun": "13-May-2025 10:11:17",
		"ini_time_size": "13-May-2025 10:00:00 19023B  MD5 = e705635ea7a200e2cedf18739f05ef41",
		"version": "Imatest 24.2.6 Master Color/Tone Auto",
		"build": "2025-03-20",
		"image_file": "potted plant_18.0 mm_100ISO_0EV_Dist2_OFF_Defocus1.tiff",
		"ColorSpace": "sRGB",
		"Reference": "Default values",
		"Ref_folder": "/usr/local/Imatest/v24.2/Master/",
		"Gamma": [0.3421],
		"patches_for_gamma_start_end": [1,5],
		"exposure_error_normalized_y_channel": [-0.113],
		"mean_camera_Saturation_Pct": ["_NaN_"],
		"mean_chroma_level_CPIQ_Pct": ["_NaN_"],
		"CPIQ_chroma_quality_loss_JND": ["_NaN_"],
		"CPIQ_exposure_quality_loss_JND": ["_NaN_"],
		"pixel_offset": [0],
		"mean_patch_size_pxls": [96,103],
		"roi_settings": "Recent ROI settings are in roi, nwid_save, nht_save, fillf, and distort (same names as ini file)",
		"roi": [3053,1801,3657,1925,3053,1927,3657,1793],
		"nwid_save": [6024],
		"nht_save": [4020],
		"fillf": [0.8],
		"distort": [0],
		"grayscale_zone": [1,2,3,4,5],
		"grayscale_minus_log_exposure": [2,1.513,1.025,0.5375,0.05],
		"grayscale_Y_reflectivity": [0.01,0.03073,0.09441,0.2901,0.8913],
		"grayscale_Y_Printer_pixel_gamma22": [33.13,55.18,91.91,153.1,255],
		"grayscale_Y_density": [0.2254,0.3393,0.5061,0.7304,1.026],
		"grayscale_R_density": [0.2289,0.3435,0.509,0.726,1.017],
		"grayscale_G_density": [0.2253,0.3384,0.5057,0.7321,1.029],
		"grayscale_B_density": [0.2163,0.3367,0.5013,0.727,1.028],
		"grayscale_Y_mean": [151.7,116.7,79.52,47.44,24.01],
		"grayscale_R_mean": [150.5,115.6,78.98,47.93,24.54],
		"grayscale_G_mean": [151.8,117,79.59,47.26,23.85],
		"grayscale_B_mean": [155,117.5,80.39,47.81,23.93],
		"White_Bal_error_Degrees": [284.4,135.9,154,-3.16,-140.7],
		"White_Bal_error_Mired": [-6.449,-3.15,-3.56,0.07482,3.403],
		"White_Bal_error_S_HSV": [0.02876,0.01558,0.01752,0.01397,0.02811],
		"White_Bal_error_Delta_C_ab": [1.856,0.6129,0.5692,0.4949,0.3625],
		"White_Bal_error_Delta_C_94": [1.856,0.6129,0.5692,0.4949,0.3625],
		"White_Bal_error_Delta_C_00": [1.791,0.761,0.5669,0.6765,0.5329],
		"n_Patch": [1,2,3,4,5],
		"n_Row": [1,1,1,1,1],
		"n_Column": [1,2,3,4,5],
		"width_pixels": [97,98,97,97,97],
		"height_pixels": [105,105,105,105,105],
		"Pixels_total": [10185,10290,10185,10185,10185],
		"R_reference": [242.4,146.6,86.6,49.01,25.46],
		"G_reference": [242.4,146.6,86.6,49.01,25.46],
		"B_reference": [242.4,146.6,86.6,49.01,25.46],
		"R_input": [150.5,115.6,78.98,47.93,24.54],
		"G_input": [151.8,117,79.59,47.26,23.85],
		"B_input": [155,117.5,80.39,47.81,23.93],
		"L_reference": [95.63,60.79,36.82,20.33,8.991],
		"a_reference": [0,0,0,0,0],
		"b_reference": [0,0,0,0,0],
		"L_input": [62.75,49.14,33.82,19.61,8.252],
		"a_input": [0.1753,-0.4232,-0.06786,0.4261,0.3572],
		"b_input": [-1.847,-0.4433,-0.5652,-0.2517,0.06194],
		"x_reference": [0.3127,0.3127,0.3127,0.3127,0.3127],
		"y_reference": [0.329,0.329,0.329,0.329,0.329],
		"Y_reference": [0.8913,0.2901,0.09441,0.03073,0.01],
		"x_input": [0.3085,0.3104,0.3103,0.3131,0.3154],
		"y_input": [0.3241,0.3281,0.3268,0.3267,0.3285],
		"Y_input": [0.3128,0.177,0.07923,0.02892,0.009139],
		"LUV_comment": "L2 is used to differentiate between the L in LAB and L in LUV.",
		"L2_reference": [805.1,262,85.28,27.75,9.033],
		"U_reference": [0.1978,0.1978,0.1978,0.1978,0.1978],
		"V_reference": [0.4683,0.4683,0.4683,0.4683,0.4683],
		"L2_input": [282.6,159.9,71.57,26.12,8.255],
		"U_input": [0.1967,0.1966,0.197,0.199,0.1999],
		"V_input": [0.465,0.4675,0.4668,0.4672,0.4685],
		"patch_numbers_for_all_Delta_E_C": [1,2,3,4,5],
		"Delta_E_all": [32.9,11.7,3.05,0.878,0.823],
		"Delta_C_all": [1.86,0.613,0.569,0.495,0.363],
		"Delta_E94_all": [32.9,11.7,3.05,0.878,0.823],
		"Delta_C94_all": [1.86,0.613,0.569,0.495,0.363],
		"Delta_E2000_all": [23,11.1,2.54,0.842,0.702],
		"Delta_C2000_all": [1.79,0.761,0.567,0.676,0.533],
		"Delta_L_all": [-32.9,-11.7,-3,-0.726,-0.739],
		"Delta_Chroma_all": [1.86,0.613,0.569,0.495,0.363],
		"Delta_Hue_Distance_all": [0,0,0,0,0],
		"Delta_Hue_Degrees_all": [0,0,0,0,0],
		"sat_corr_comment": "sat_corr explained on https://www.imatest.com/docs/colorcheck/#satcorr - not recommended.",
		"Delta_C_all_sat_corr": ["_NaN_","_NaN_","_NaN_","_NaN_","_NaN_"],
		"Delta_C94_all_sat_corr": ["_NaN_","_NaN_","_NaN_","_NaN_","_NaN_"],
		"Delta_C2000_all_sat_corr": ["_NaN_","_NaN_","_NaN_","_NaN_","_NaN_"],
		"grayscale_patch_numbers": [1,2,3,4,5],
		"Delta_E": [32.9,11.7,3.05,0.878,0.823],
		"Delta_C": [1.86,0.613,0.569,0.495,0.363],
		"Delta_E94": [32.9,11.7,3.05,0.878,0.823],
		"Delta_C94": [1.86,0.613,0.569,0.495,0.363],
		"Delta_E2000": [23,11.1,2.54,0.842,0.702],
		"Delta_C2000": [1.79,0.761,0.567,0.676,0.533],
		"Delta_L": [-32.9,-11.7,-3,-0.726,-0.739],
		"Delta_Chroma": [1.86,0.613,0.569,0.495,0.363],
		"Delta_Hue_Distance": [0,0,0,0,0],
		"Delta_Hue_Degrees": [0,0,0,0,0],
		"mean_Delta_E": [9.87],
		"mean_Delta_C": [0.779],
		"mean_Delta_E94": [9.87],
		"mean_Delta_C94": [0.779],
		"mean_Delta_E2000": [7.63],
		"mean_Delta_C2000": [0.866],
		"mean_Delta_L": [-9.8],
		"mean_Delta_Chroma": [0.779],
		"mean_Delta_Hue_Distance": [0],
		"mean_Delta_Hue_Degrees": [0],
		"mean_Delta_C_sat_corr": ["_NaN_"],
		"mean_Delta_C94_sat_corr": ["_NaN_"],
		"mean_Delta_C2000_sat_corr": ["_NaN_"],
		"max_Delta_E": [32.9],
		"max_Delta_C": [1.86],
		"max_Delta_E94": [32.9],
		"max_Delta_C94": [1.86],
		"max_Delta_E2000": [23],
		"max_Delta_C2000": [1.79],
		"max_Delta_L": [-0.726],
		"max_Delta_Chroma": [1.86],
		"max_Delta_Hue_Distance": [0],
		"max_Delta_Hue_Degrees": [0],
		"max_Delta_C_sat_corr": ["_NaN_"],
		"max_Delta_C94_sat_corr": ["_NaN_"],
		"max_Delta_C2000_sat_corr": ["_NaN_"],
		"mean_RegionSize": [10108.8],
		"Sequence_dark_to_light": [5,4,3,2,1],
		"Patch_number": [5,4,3,2,1],
		"R_noise": [0.01619,0.007626,0.006035,0.006101,0.00622],
		"G_noise": [0.0169,0.006318,0.003944,0.004326,0.004813],
		"B_noise": [0.01473,0.006342,0.005139,0.005294,0.005276],
		"R_SNR_ratio": [5.944,24.65,51.32,74.32,94.91],
		"G_SNR_ratio": [5.535,29.33,79.14,106,123.7],
		"B_SNR_ratio": [6.372,29.56,61.34,87.01,115.2],
		"R_SNR_dB": [15.48,27.84,34.21,37.42,39.55],
		"G_SNR_dB": [14.86,29.35,37.97,40.51,41.84],
		"B_SNR_dB": [16.09,29.42,35.76,38.79,41.23],
		"Gb_noise": [0.01614,0.005785,0.003344,0.003829,0.004249],
		"Gb_SNR_ratio": [5.832,32.16,93.26,119.6,140],
		"Gb_SNR_dB": [15.32,30.15,39.39,41.55,42.93],
		"Y_f_stop_SNR_ratio": [19.95,22.83,25.09,11.62,3.515],
		"Y_f_stop_SNR_dB": [26,27.17,27.99,21.3,10.92],
		"quality_levels_for_DR": [
				"Low,",
				"Medium,",
				"M-H,",
				"High,"
		],
		"SigNoise_levels_for_DR": [1,0.5,0.25,0.1],
		"Dynamic_Range_f_stops": [0,0,6.196,4.972],
		"Dynamic_Range_dB": [0,0,37.3,29.93],
		"noise_ISO15739_pct": [0.1276,0.06335,0.08711,0.2348,0.3543],
		"snr_ISO15739": [7.162,45.65,90.95,75.42,88.29],
		"noise_pct_ISO15739_at_13pct_Lref": [0.3005],
		"snr_ISO15739_at_13pct_Lref": [82.5],
		"snr_dB_ISO15739_at_13pct_Lref": [38.33],
		"DynamicRange_at_density_2": [3742],
		"DynamicRange_total": [0],
		"DynamicRange_from_slope_OD": [1.95],
		"DynamicRange_from_slope_EV": [6.474],
		"DynamicRange_from_slope_dB": [39],
		"SNR_BW_dB_RGBY": [36.53,39.51,37.76,40.57],
		"L_noise": [2.004,0.6775,0.363,0.3891,0.4115],
		"a_noise": [1.29,1.009,0.8809,0.7853,0.7543],
		"b_noise": [1.323,1.019,0.8931,0.8071,0.7947],
		"Total_Lab_noise_unwtd": [2.726,1.586,1.306,1.191,1.17],
		"Total_ab_noise_unwtd": [1.848,1.434,1.254,1.126,1.096],
		"R_minus_Y_KK_noise": [0.006264,0.005225,0.005067,0.004781,0.004753],
		"B_minus_Y_KK_noise": [0.007184,0.005822,0.005539,0.005352,0.005527],
		"Y_Kelly_Keelan_noise": [0.01614,0.005785,0.003344,0.003829,0.004249],
		"Total_KK_noise": [0.01661,0.006638,0.004587,0.004854,0.005201],
		"Chroma_KK_noise": [0.003936,0.003256,0.00314,0.002983,0.002999],
		"Total_old_iso_noise": [0.01714,0.007507,0.005703,0.00582,0.006116],
		"Y_noise_from_YUV": [0.01614,0.005784,0.003344,0.003829,0.004249],
		"U_noise_from_YUV": [0.003375,0.002736,0.002603,0.002515,0.002597],
		"V_noise_from_YUV": [0.004892,0.004081,0.003957,0.003734,0.003712],
		"Total_UV_noise_from_YUV": [0.005943,0.004913,0.004736,0.004501,0.00453],
		"R_minus_Y_KK_SNR_dB": [23.54,31.03,35.78,39.62,41.95],
		"B_minus_Y_KK_SNR_dB": [22.35,30.09,35.01,38.64,40.64],
		"Y_Kelly_Keelan_SNR_dB": [15.32,30.15,39.39,41.55,42.93],
		"Total_KK_SNR_dB": [15.07,28.95,36.65,39.49,41.17],
		"Chroma_KK_SNR_dB": [27.58,35.14,39.94,43.72,45.95],
		"Total_old_iso_SNR_dB": [14.79,27.88,34.76,37.91,39.76],
		"Y_SNR_dB_from_YUV": [15.32,30.15,39.39,41.55,42.93],
		"U_SNR_dB_from_YUV": [28.91,36.65,41.57,45.2,47.2],
		"V_SNR_dB_from_YUV": [25.69,33.18,37.93,41.77,44.1],
		"Total_UV_SNR_dB_from_YUV": [24,31.57,36.37,40.15,42.37],
		"gain_incremental": [1.2,1.63,3.84,9.13,12.6],
		"SNR_ISO_Q": [0.2693],
		"VN_distance_1_cm": [40],
		"VN_height_1_cm": [25],
		"VN_angle_1_deg": [34.71],
		"VN_mean_L_1": [7.682,19.59,33.84,49.14,62.77],
		"VN_sigma_L_1": [4.983,1.525,0.5814,0.7633,0.7291],
		"VN_sigma_u_1": [0.3273,0.37,0.3526,0.3475,0.3595],
		"VN_sigma_v_1": [0.3304,0.2025,0.1686,0.2179,0.2255],
		"VN_sigma_Visnoise_1": [5.368,1.906,0.9362,1.13,1.108],
		"VN_SNR_L_1": [1.542,12.85,58.21,64.38,86.09],
		"VN_SNR_u_1": [23.47,52.95,95.98,141.4,174.6],
		"VN_SNR_v_1": [23.25,96.75,200.7,225.5,278.4],
		"VN_SNR_Visnoise_1": [1.431,10.28,36.14,43.5,56.64],
		"EXIF_results": [
				"File Modification Date/Time     , 2025:04:22 20:58:39+02:00",
				"Image Width                     , 6024",
				"Image Height                    , 4020"
		]
	}
}
